{
  "unpublishedPage": {
    "name": "页面1",
    "slug": "1",
    "layouts": [
      {
        "viewMode": false,
        "dsl": {
          "widgetName": "MainContainer",
          "backgroundColor": "none",
          "rightColumn": 1224,
          "snapColumns": 64,
          "detachFromLayout": true,
          "widgetId": "0",
          "topRow": 0,
          "bottomRow": 1440,
          "containerStyle": "none",
          "snapRows": 44,
          "parentRowSpace": 1,
          "type": "CANVAS_WIDGET",
          "canExtend": true,
          "version": 71,
          "minHeight": 450,
          "parentColumnSpace": 1,
          "dynamicBindingPathList": [],
          "leftColumn": 0,
          "children": [
            {
              "boxShadow": "none",
              "widgetName": "Input1",
              "displayName": "输入框",
              "iconSVG": "/static/media/icon.9f505595da61a34f563dba82adeb06ec.svg",
              "searchTags": [
                "form",
                "text input",
                "number",
                "textarea"
              ],
              "topRow": 7,
              "bottomRow": 14,
              "parentRowSpace": 10,
              "labelWidth": 5,
              "autoFocus": false,
              "type": "INPUT_WIDGET_V2",
              "hideCard": false,
              "animateLoading": true,
              "parentColumnSpace": 10.0625,
              "resetOnSubmit": true,
              "leftColumn": 12,
              "dynamicBindingPathList": [
                {
                  "key": "accentColor"
                },
                {
                  "key": "borderRadius"
                }
              ],
              "labelPosition": "Top",
              "labelStyle": "",
              "inputType": "TEXT",
              "isDisabled": false,
              "key": "s665zo4vds",
              "labelTextSize": "0.875rem",
              "isRequired": false,
              "isDeprecated": false,
              "rightColumn": 32,
              "dynamicHeight": "FIXED",
              "widgetId": "7prcy41grr",
              "accentColor": "{{appsmith.theme.colors.primaryColor}}",
              "isVisible": true,
              "label": "标签",
              "version": 2,
              "parentId": "0",
              "labelAlignment": "left",
              "renderMode": "CANVAS",
              "isLoading": false,
              "borderRadius": "{{appsmith.theme.borderRadius.appBorderRadius}}",
              "maxDynamicHeight": 9000,
              "iconAlign": "left",
              "defaultText": "",
              "minDynamicHeight": 4
            },
            {
              "boxShadow": "none",
              "widgetName": "Input2",
              "displayName": "输入框",
              "iconSVG": "/static/media/icon.9f505595da61a34f563dba82adeb06ec.svg",
              "searchTags": [
                "form",
                "text input",
                "number",
                "textarea"
              ],
              "topRow": 15,
              "bottomRow": 22,
              "tooltip": "",
              "parentRowSpace": 10,
              "labelWidth": 5,
              "autoFocus": true,
              "type": "INPUT_WIDGET_V2",
              "hideCard": false,
              "animateLoading": true,
              "parentColumnSpace": 10.0625,
              "dynamicTriggerPathList": [
                {
                  "key": "onBlur"
                }
              ],
              "resetOnSubmit": true,
              "leftColumn": 12,
              "dynamicBindingPathList": [
                {
                  "key": "accentColor"
                },
                {
                  "key": "borderRadius"
                },
                {
                  "key": "defaultText"
                }
              ],
              "labelPosition": "Top",
              "labelStyle": "",
              "inputType": "TEXT",
              "placeholderText": "",
              "isDisabled": false,
              "key": "s665zo4vds",
              "labelTextSize": "0.875rem",
              "isRequired": false,
              "isDeprecated": false,
              "rightColumn": 32,
              "dynamicHeight": "FIXED",
              "widgetId": "tqtpzzovj4",
              "accentColor": "{{appsmith.theme.colors.primaryColor}}",
              "isVisible": true,
              "label": "标签",
              "version": 2,
              "parentId": "0",
              "labelAlignment": "left",
              "renderMode": "CANVAS",
              "isLoading": false,
              "onBlur": "{{storeValue('a','xxxin')}}",
              "borderRadius": "{{appsmith.theme.borderRadius.appBorderRadius}}",
              "maxDynamicHeight": 9000,
              "iconAlign": "left",
              "defaultText": "{{global.store.res}}",
              "minDynamicHeight": 4
            },
            {
              "resetFormOnClick": false,
              "boxShadow": "none",
              "widgetName": "Button1",
              "onClick": "{{JSObject2.myFun1()}}",
              "buttonColor": "{{appsmith.theme.colors.primaryColor}}",
              "displayName": "按钮",
              "iconSVG": "/static/media/icon.cca026338f1c8eb6df8ba03d084c2fca.svg",
              "searchTags": [
                "click",
                "submit",
                "button"
              ],
              "topRow": 25,
              "bottomRow": 29,
              "tooltip": "",
              "parentRowSpace": 10,
              "type": "BUTTON_WIDGET",
              "hideCard": false,
              "animateLoading": true,
              "parentColumnSpace": 10.0625,
              "dynamicTriggerPathList": [
                {
                  "key": "onClick"
                }
              ],
              "leftColumn": 12,
              "dynamicBindingPathList": [
                {
                  "key": "buttonColor"
                },
                {
                  "key": "borderRadius"
                }
              ],
              "text": "提交",
              "isDisabled": false,
              "key": "a7wa99uuqy",
              "isDeprecated": false,
              "rightColumn": 28,
              "isDefaultClickDisabled": true,
              "widgetId": "aqicdh5q6k",
              "isVisible": false,
              "recaptchaType": "V3",
              "version": 1,
              "parentId": "0",
              "renderMode": "CANVAS",
              "isLoading": false,
              "disabledWhenInvalid": false,
              "borderRadius": "{{appsmith.theme.borderRadius.appBorderRadius}}",
              "buttonVariant": "PRIMARY",
              "placement": "CENTER"
            },
            {
              "boxShadow": "none",
              "widgetName": "Modal1",
              "isCanvas": true,
              "displayName": "弹窗",
              "iconSVG": "/static/media/icon.4975978e9a961fb0bfb4e38de7ecc7c5.svg",
              "searchTags": [
                "dialog",
                "popup",
                "notification",
                "modal"
              ],
              "topRow": 0,
              "bottomRow": 240,
              "parentRowSpace": 1,
              "type": "MODAL_WIDGET",
              "hideCard": false,
              "shouldScrollContents": true,
              "animateLoading": true,
              "parentColumnSpace": 1,
              "leftColumn": 0,
              "dynamicBindingPathList": [
                {
                  "key": "borderRadius"
                }
              ],
              "children": [
                {
                  "widgetName": "Canvas1",
                  "displayName": "Canvas",
                  "topRow": 0,
                  "bottomRow": 240,
                  "parentRowSpace": 1,
                  "type": "CANVAS_WIDGET",
                  "canExtend": true,
                  "hideCard": true,
                  "shouldScrollContents": false,
                  "minHeight": 240,
                  "parentColumnSpace": 1,
                  "leftColumn": 0,
                  "dynamicBindingPathList": [],
                  "children": [
                    {
                      "boxShadow": "none",
                      "widgetName": "IconButton1",
                      "onClick": "{{closeModal('Modal1')}}",
                      "buttonColor": "{{appsmith.theme.colors.primaryColor}}",
                      "displayName": "图标按钮",
                      "iconSVG": "/static/media/icon.1a0c634ac75f9fa6b6ae7a8df882a3ba.svg",
                      "searchTags": [
                        "click",
                        "submit",
                        "icon button"
                      ],
                      "topRow": 0,
                      "bottomRow": 4,
                      "type": "ICON_BUTTON_WIDGET",
                      "hideCard": false,
                      "animateLoading": true,
                      "leftColumn": 58,
                      "dynamicBindingPathList": [
                        {
                          "key": "buttonColor"
                        },
                        {
                          "key": "borderRadius"
                        }
                      ],
                      "iconSize": 24,
                      "isDisabled": false,
                      "key": "awgx3jwytm",
                      "isDeprecated": false,
                      "rightColumn": 64,
                      "iconName": "cross",
                      "widgetId": "ucphxez96o",
                      "isVisible": true,
                      "version": 1,
                      "parentId": "5fhg9hwmz8",
                      "renderMode": "CANVAS",
                      "isLoading": false,
                      "borderRadius": "{{appsmith.theme.borderRadius.appBorderRadius}}",
                      "buttonVariant": "TERTIARY"
                    },
                    {
                      "widgetName": "Text1",
                      "displayName": "文本",
                      "iconSVG": "/static/media/icon.97c59b523e6f70ba6f40a10fc2c7c5b5.svg",
                      "searchTags": [
                        "typography",
                        "paragraph",
                        "label",
                        "text",
                        "文字",
                        "标题",
                        "段落",
                        "字符"
                      ],
                      "topRow": 1,
                      "bottomRow": 5,
                      "type": "TEXT_WIDGET",
                      "hideCard": false,
                      "animateLoading": true,
                      "overflow": "NONE",
                      "fontFamily": "{{appsmith.theme.fontFamily.appFont}}",
                      "leftColumn": 1,
                      "dynamicBindingPathList": [
                        {
                          "key": "truncateButtonColor"
                        },
                        {
                          "key": "fontFamily"
                        },
                        {
                          "key": "borderRadius"
                        }
                      ],
                      "shouldTruncate": false,
                      "truncateButtonColor": "{{appsmith.theme.colors.primaryColor}}",
                      "text": "弹窗标题",
                      "key": "bw3zai5t0s",
                      "isDeprecated": false,
                      "rightColumn": 41,
                      "textAlign": "LEFT",
                      "dynamicHeight": "AUTO_HEIGHT",
                      "widgetId": "pm5h0ct2df",
                      "isVisible": true,
                      "fontStyle": "BOLD",
                      "textColor": "#231F20",
                      "version": 1,
                      "parentId": "5fhg9hwmz8",
                      "renderMode": "CANVAS",
                      "isLoading": false,
                      "borderRadius": "{{appsmith.theme.borderRadius.appBorderRadius}}",
                      "maxDynamicHeight": 9000,
                      "fontSize": "1.25rem",
                      "minDynamicHeight": 4
                    },
                    {
                      "resetFormOnClick": false,
                      "boxShadow": "none",
                      "widgetName": "Button2",
                      "buttonColor": "{{appsmith.theme.colors.primaryColor}}",
                      "displayName": "按钮",
                      "iconSVG": "/static/media/icon.cca026338f1c8eb6df8ba03d084c2fca.svg",
                      "searchTags": [
                        "click",
                        "submit",
                        "button"
                      ],
                      "topRow": 18,
                      "bottomRow": 22,
                      "type": "BUTTON_WIDGET",
                      "hideCard": false,
                      "animateLoading": true,
                      "leftColumn": 31,
                      "dynamicBindingPathList": [
                        {
                          "key": "buttonColor"
                        },
                        {
                          "key": "borderRadius"
                        }
                      ],
                      "text": "关闭",
                      "isDisabled": false,
                      "key": "a7wa99uuqy",
                      "isDeprecated": false,
                      "rightColumn": 47,
                      "isDefaultClickDisabled": true,
                      "widgetId": "vfvguebprz",
                      "buttonStyle": "PRIMARY",
                      "isVisible": true,
                      "recaptchaType": "V3",
                      "version": 1,
                      "parentId": "5fhg9hwmz8",
                      "renderMode": "CANVAS",
                      "isLoading": false,
                      "disabledWhenInvalid": false,
                      "borderRadius": "{{appsmith.theme.borderRadius.appBorderRadius}}",
                      "buttonVariant": "SECONDARY",
                      "placement": "CENTER"
                    },
                    {
                      "resetFormOnClick": false,
                      "boxShadow": "none",
                      "widgetName": "Button3",
                      "buttonColor": "{{appsmith.theme.colors.primaryColor}}",
                      "displayName": "按钮",
                      "iconSVG": "/static/media/icon.cca026338f1c8eb6df8ba03d084c2fca.svg",
                      "searchTags": [
                        "click",
                        "submit",
                        "button"
                      ],
                      "topRow": 18,
                      "bottomRow": 22,
                      "type": "BUTTON_WIDGET",
                      "hideCard": false,
                      "animateLoading": true,
                      "leftColumn": 47,
                      "dynamicBindingPathList": [
                        {
                          "key": "buttonColor"
                        },
                        {
                          "key": "borderRadius"
                        }
                      ],
                      "text": "确定",
                      "isDisabled": false,
                      "key": "a7wa99uuqy",
                      "isDeprecated": false,
                      "rightColumn": 63,
                      "isDefaultClickDisabled": true,
                      "widgetId": "ij2q6odoap",
                      "buttonStyle": "PRIMARY_BUTTON",
                      "isVisible": true,
                      "recaptchaType": "V3",
                      "version": 1,
                      "parentId": "5fhg9hwmz8",
                      "renderMode": "CANVAS",
                      "isLoading": false,
                      "disabledWhenInvalid": false,
                      "borderRadius": "{{appsmith.theme.borderRadius.appBorderRadius}}",
                      "buttonVariant": "PRIMARY",
                      "placement": "CENTER"
                    }
                  ],
                  "isDisabled": false,
                  "key": "wka2xql8aj",
                  "isDeprecated": false,
                  "rightColumn": 0,
                  "detachFromLayout": true,
                  "widgetId": "5fhg9hwmz8",
                  "isVisible": true,
                  "version": 1,
                  "parentId": "mvdyrsd0cs",
                  "renderMode": "CANVAS",
                  "isLoading": false
                }
              ],
              "key": "fm9ho0jpn2",
              "height": 240,
              "isDeprecated": false,
              "rightColumn": 0,
              "detachFromLayout": true,
              "dynamicHeight": "AUTO_HEIGHT",
              "widgetId": "mvdyrsd0cs",
              "canOutsideClickClose": true,
              "canEscapeKeyClose": true,
              "version": 2,
              "parentId": "0",
              "renderMode": "CANVAS",
              "isLoading": false,
              "borderRadius": "{{appsmith.theme.borderRadius.appBorderRadius}}",
              "maxDynamicHeight": 9000,
              "width": 456,
              "minDynamicHeight": 24
            },
            {
              "schema": {
                "__root_schema__": {
                  "children": {
                    "name": {
                      "children": {},
                      "dataType": "string",
                      "defaultValue": "{{((sourceData, formData, fieldState) => (sourceData.name))(JSONForm1.sourceData, JSONForm1.formData, JSONForm1.fieldState)}}",
                      "fieldType": "Text Input",
                      "sourceData": "John Wick",
                      "isCustomField": false,
                      "accessor": "name",
                      "identifier": "name",
                      "position": 0,
                      "originalIdentifier": "name",
                      "accentColor": "{{((sourceData, formData, fieldState) => (appsmith.theme.colors.primaryColor))(JSONForm1.sourceData, JSONForm1.formData, JSONForm1.fieldState)}}",
                      "borderRadius": "{{((sourceData, formData, fieldState) => (appsmith.theme.borderRadius.appBorderRadius))(JSONForm1.sourceData, JSONForm1.formData, JSONForm1.fieldState)}}",
                      "boxShadow": "none",
                      "iconAlign": "left",
                      "isDisabled": false,
                      "isRequired": false,
                      "isSpellCheck": false,
                      "isVisible": true,
                      "labelTextSize": "0.875rem",
                      "label": "Name"
                    },
                    "date_of_birth": {
                      "children": {},
                      "dataType": "string",
                      "defaultValue": "{{((sourceData, formData, fieldState) => (moment(sourceData.date_of_birth, \"DD/MM/YYYY\").format(\"YYYY-MM-DDTHH:mm:ss.sssZ\")))(JSONForm1.sourceData, JSONForm1.formData, JSONForm1.fieldState)}}",
                      "fieldType": "Datepicker",
                      "sourceData": "20/02/1990",
                      "isCustomField": false,
                      "accessor": "date_of_birth",
                      "identifier": "date_of_birth",
                      "position": 1,
                      "originalIdentifier": "date_of_birth",
                      "accentColor": "{{((sourceData, formData, fieldState) => (appsmith.theme.colors.primaryColor))(JSONForm1.sourceData, JSONForm1.formData, JSONForm1.fieldState)}}",
                      "borderRadius": "{{((sourceData, formData, fieldState) => (appsmith.theme.borderRadius.appBorderRadius))(JSONForm1.sourceData, JSONForm1.formData, JSONForm1.fieldState)}}",
                      "boxShadow": "none",
                      "closeOnSelection": false,
                      "convertToISO": false,
                      "dateFormat": "DD/MM/YYYY",
                      "isDisabled": false,
                      "isRequired": false,
                      "isVisible": true,
                      "label": "Date Of Birth",
                      "maxDate": "2121-12-31T18:29:00.000Z",
                      "minDate": "1920-12-31T18:30:00.000Z",
                      "shortcuts": false,
                      "timePrecision": "minute",
                      "labelTextSize": "0.875rem"
                    },
                    "employee_id": {
                      "children": {},
                      "dataType": "number",
                      "defaultValue": "{{((sourceData, formData, fieldState) => (sourceData.employee_id))(JSONForm1.sourceData, JSONForm1.formData, JSONForm1.fieldState)}}",
                      "fieldType": "Number Input",
                      "sourceData": 1001,
                      "isCustomField": false,
                      "accessor": "employee_id",
                      "identifier": "employee_id",
                      "position": 2,
                      "originalIdentifier": "employee_id",
                      "accentColor": "{{((sourceData, formData, fieldState) => (appsmith.theme.colors.primaryColor))(JSONForm1.sourceData, JSONForm1.formData, JSONForm1.fieldState)}}",
                      "borderRadius": "{{((sourceData, formData, fieldState) => (appsmith.theme.borderRadius.appBorderRadius))(JSONForm1.sourceData, JSONForm1.formData, JSONForm1.fieldState)}}",
                      "boxShadow": "none",
                      "iconAlign": "left",
                      "isDisabled": false,
                      "isRequired": false,
                      "isSpellCheck": false,
                      "isVisible": true,
                      "labelTextSize": "0.875rem",
                      "label": "Employee Id"
                    },
                    "customField1": {
                      "children": {},
                      "dataType": "string",
                      "defaultValue": "",
                      "fieldType": "Multiline Text Input",
                      "sourceData": "",
                      "isCustomField": true,
                      "accessor": "customField1",
                      "identifier": "customField1",
                      "position": 3,
                      "originalIdentifier": "customField1",
                      "accentColor": "{{((sourceData, formData, fieldState) => (appsmith.theme.colors.primaryColor))(JSONForm1.sourceData, JSONForm1.formData, JSONForm1.fieldState)}}",
                      "borderRadius": "{{((sourceData, formData, fieldState) => (appsmith.theme.borderRadius.appBorderRadius))(JSONForm1.sourceData, JSONForm1.formData, JSONForm1.fieldState)}}",
                      "boxShadow": "none",
                      "iconAlign": "left",
                      "isDisabled": false,
                      "isRequired": false,
                      "isSpellCheck": false,
                      "isVisible": true,
                      "labelTextSize": "0.875rem",
                      "label": "Custom Field "
                    }
                  },
                  "dataType": "object",
                  "defaultValue": "{{((sourceData, formData, fieldState) => (sourceData))(JSONForm1.sourceData, JSONForm1.formData, JSONForm1.fieldState)}}",
                  "fieldType": "Object",
                  "sourceData": {
                    "name": "John Wick",
                    "date_of_birth": "20/02/1990",
                    "employee_id": 1001
                  },
                  "isCustomField": false,
                  "accessor": "__root_schema__",
                  "identifier": "__root_schema__",
                  "position": -1,
                  "originalIdentifier": "__root_schema__",
                  "borderRadius": "{{((sourceData, formData, fieldState) => (appsmith.theme.borderRadius.appBorderRadius))(JSONForm1.sourceData, JSONForm1.formData, JSONForm1.fieldState)}}",
                  "boxShadow": "none",
                  "cellBorderRadius": "{{((sourceData, formData, fieldState) => (appsmith.theme.borderRadius.appBorderRadius))(JSONForm1.sourceData, JSONForm1.formData, JSONForm1.fieldState)}}",
                  "cellBoxShadow": "none",
                  "isDisabled": false,
                  "isRequired": false,
                  "isVisible": true,
                  "labelTextSize": "0.875rem",
                  "label": ""
                }
              },
              "boxShadow": "{{appsmith.theme.boxShadow.appBoxShadow}}",
              "borderColor": "#E0DEDE",
              "widgetName": "JSONForm1",
              "submitButtonStyles": {
                "buttonColor": "{{appsmith.theme.colors.primaryColor}}",
                "borderRadius": "{{appsmith.theme.borderRadius.appBorderRadius}}",
                "boxShadow": "none",
                "buttonVariant": "PRIMARY"
              },
              "dynamicPropertyPathList": [
                {
                  "key": "schema.__root_schema__.children.date_of_birth.defaultValue"
                }
              ],
              "displayName": "JSON表单",
              "iconSVG": "/static/media/icon.5b428de12db9ad6a591955ead07f86e9.svg",
              "onSubmit": "{{Api2.run()}}",
              "searchTags": [
                "json form"
              ],
              "topRow": 67,
              "bottomRow": 136,
              "fieldLimitExceeded": false,
              "parentRowSpace": 10,
              "title": "表单",
              "type": "JSON_FORM_WIDGET",
              "hideCard": false,
              "animateLoading": true,
              "parentColumnSpace": 10.0625,
              "dynamicTriggerPathList": [
                {
                  "key": "onSubmit"
                }
              ],
              "leftColumn": 7,
              "dynamicBindingPathList": [
                {
                  "key": "borderRadius"
                },
                {
                  "key": "boxShadow"
                },
                {
                  "key": "submitButtonStyles.buttonColor"
                },
                {
                  "key": "submitButtonStyles.borderRadius"
                },
                {
                  "key": "resetButtonStyles.buttonColor"
                },
                {
                  "key": "resetButtonStyles.borderRadius"
                },
                {
                  "key": "schema.__root_schema__.children.name.defaultValue"
                },
                {
                  "key": "schema.__root_schema__.children.name.accentColor"
                },
                {
                  "key": "schema.__root_schema__.children.name.borderRadius"
                },
                {
                  "key": "schema.__root_schema__.children.date_of_birth.defaultValue"
                },
                {
                  "key": "schema.__root_schema__.children.date_of_birth.accentColor"
                },
                {
                  "key": "schema.__root_schema__.children.date_of_birth.borderRadius"
                },
                {
                  "key": "schema.__root_schema__.children.employee_id.defaultValue"
                },
                {
                  "key": "schema.__root_schema__.children.employee_id.accentColor"
                },
                {
                  "key": "schema.__root_schema__.children.employee_id.borderRadius"
                },
                {
                  "key": "schema.__root_schema__.defaultValue"
                },
                {
                  "key": "schema.__root_schema__.borderRadius"
                },
                {
                  "key": "schema.__root_schema__.cellBorderRadius"
                },
                {
                  "key": "schema.__root_schema__.children.customField1.borderRadius"
                },
                {
                  "key": "schema.__root_schema__.children.customField1.accentColor"
                }
              ],
              "borderWidth": "1",
              "sourceData": {
                "name": "John Wick",
                "date_of_birth": "20/02/1990",
                "employee_id": 1001
              },
              "showReset": true,
              "resetButtonLabel": "重置",
              "key": "ipja6862ts",
              "backgroundColor": "#fff",
              "isDeprecated": false,
              "rightColumn": 64,
              "dynamicHeight": "FIXED",
              "autoGenerateForm": true,
              "widgetId": "05d0gn89h4",
              "resetButtonStyles": {
                "buttonColor": "{{appsmith.theme.colors.primaryColor}}",
                "borderRadius": "{{appsmith.theme.borderRadius.appBorderRadius}}",
                "boxShadow": "none",
                "buttonVariant": "SECONDARY"
              },
              "isVisible": true,
              "version": 1,
              "parentId": "0",
              "renderMode": "CANVAS",
              "isLoading": false,
              "scrollContents": true,
              "fixedFooter": true,
              "submitButtonLabel": "提交",
              "childStylesheet": {
                "ARRAY": {
                  "accentColor": "{{appsmith.theme.colors.primaryColor}}",
                  "borderRadius": "{{appsmith.theme.borderRadius.appBorderRadius}}",
                  "boxShadow": "none",
                  "cellBorderRadius": "{{appsmith.theme.borderRadius.appBorderRadius}}",
                  "cellBoxShadow": "none"
                },
                "OBJECT": {
                  "borderRadius": "{{appsmith.theme.borderRadius.appBorderRadius}}",
                  "boxShadow": "none",
                  "cellBorderRadius": "{{appsmith.theme.borderRadius.appBorderRadius}}",
                  "cellBoxShadow": "none"
                },
                "CHECKBOX": {
                  "accentColor": "{{appsmith.theme.colors.primaryColor}}",
                  "borderRadius": "{{appsmith.theme.borderRadius.appBorderRadius}}"
                },
                "CURRENCY_INPUT": {
                  "accentColor": "{{appsmith.theme.colors.primaryColor}}",
                  "borderRadius": "{{appsmith.theme.borderRadius.appBorderRadius}}",
                  "boxShadow": "none"
                },
                "DATEPICKER": {
                  "accentColor": "{{appsmith.theme.colors.primaryColor}}",
                  "borderRadius": "{{appsmith.theme.borderRadius.appBorderRadius}}",
                  "boxShadow": "none"
                },
                "EMAIL_INPUT": {
                  "accentColor": "{{appsmith.theme.colors.primaryColor}}",
                  "borderRadius": "{{appsmith.theme.borderRadius.appBorderRadius}}",
                  "boxShadow": "none"
                },
                "MULTISELECT": {
                  "accentColor": "{{appsmith.theme.colors.primaryColor}}",
                  "borderRadius": "{{appsmith.theme.borderRadius.appBorderRadius}}",
                  "boxShadow": "none"
                },
                "MULTILINE_TEXT_INPUT": {
                  "accentColor": "{{appsmith.theme.colors.primaryColor}}",
                  "borderRadius": "{{appsmith.theme.borderRadius.appBorderRadius}}",
                  "boxShadow": "none"
                },
                "NUMBER_INPUT": {
                  "accentColor": "{{appsmith.theme.colors.primaryColor}}",
                  "borderRadius": "{{appsmith.theme.borderRadius.appBorderRadius}}",
                  "boxShadow": "none"
                },
                "PASSWORD_INPUT": {
                  "accentColor": "{{appsmith.theme.colors.primaryColor}}",
                  "borderRadius": "{{appsmith.theme.borderRadius.appBorderRadius}}",
                  "boxShadow": "none"
                },
                "PHONE_NUMBER_INPUT": {
                  "accentColor": "{{appsmith.theme.colors.primaryColor}}",
                  "borderRadius": "{{appsmith.theme.borderRadius.appBorderRadius}}",
                  "boxShadow": "none"
                },
                "RADIO_GROUP": {
                  "accentColor": "{{appsmith.theme.colors.primaryColor}}",
                  "boxShadow": "none"
                },
                "SELECT": {
                  "accentColor": "{{appsmith.theme.colors.primaryColor}}",
                  "borderRadius": "{{appsmith.theme.borderRadius.appBorderRadius}}",
                  "boxShadow": "none"
                },
                "SWITCH": {
                  "accentColor": "{{appsmith.theme.colors.primaryColor}}",
                  "boxShadow": "none"
                },
                "TEXT_INPUT": {
                  "accentColor": "{{appsmith.theme.colors.primaryColor}}",
                  "borderRadius": "{{appsmith.theme.borderRadius.appBorderRadius}}",
                  "boxShadow": "none"
                }
              },
              "disabledWhenInvalid": true,
              "borderRadius": "{{appsmith.theme.borderRadius.appBorderRadius}}",
              "maxDynamicHeight": 9000,
              "minDynamicHeight": 4
            },
            {
              "boxShadow": "{{appsmith.theme.boxShadow.appBoxShadow}}",
              "widgetName": "Container1",
              "borderColor": "#E0DEDE",
              "isCanvas": true,
              "displayName": "容器",
              "iconSVG": "/static/media/icon.1977dca3370505e2db3a8e44cfd54907.svg",
              "searchTags": [
                "div",
                "parent",
                "group",
                "container"
              ],
              "topRow": 14,
              "bottomRow": 24,
              "parentRowSpace": 10,
              "type": "CONTAINER_WIDGET",
              "hideCard": false,
              "shouldScrollContents": true,
              "animateLoading": true,
              "parentColumnSpace": 10.0625,
              "leftColumn": 36,
              "dynamicBindingPathList": [
                {
                  "key": "borderRadius"
                },
                {
                  "key": "boxShadow"
                }
              ],
              "children": [
                {
                  "widgetName": "Canvas2",
                  "displayName": "Canvas",
                  "topRow": 0,
                  "bottomRow": 100,
                  "parentRowSpace": 1,
                  "type": "CANVAS_WIDGET",
                  "canExtend": false,
                  "hideCard": true,
                  "minHeight": 100,
                  "parentColumnSpace": 1,
                  "leftColumn": 0,
                  "dynamicBindingPathList": [],
                  "children": [],
                  "key": "nhs3te0xpr",
                  "isDeprecated": false,
                  "rightColumn": 241.5,
                  "detachFromLayout": true,
                  "widgetId": "kq6n59a722",
                  "containerStyle": "none",
                  "isVisible": true,
                  "version": 1,
                  "parentId": "71yz1o20gl",
                  "renderMode": "CANVAS",
                  "isLoading": false
                }
              ],
              "borderWidth": "1",
              "key": "s0uawswvnm",
              "backgroundColor": "#FFFFFF",
              "isDeprecated": false,
              "rightColumn": 60,
              "dynamicHeight": "AUTO_HEIGHT",
              "widgetId": "71yz1o20gl",
              "containerStyle": "card",
              "isVisible": true,
              "version": 1,
              "parentId": "0",
              "renderMode": "CANVAS",
              "isLoading": false,
              "borderRadius": "{{appsmith.theme.borderRadius.appBorderRadius}}",
              "maxDynamicHeight": 9000,
              "minDynamicHeight": 10
            }
          ]
        },
        "layoutOnLoadActions": [],
        "layoutOnLoadActionErrors": [],
        "validOnPageLoadActions": true,
        "id": "页面1",
        "deleted": false,
        "policies": [],
        "userPermissions": []
      }
    ],
    "userPermissions": [],
    "policies": []
  },
  "deleted": false,
  "gitSyncId": "6571645002f2017cc3d3b687_6571884102f2017cc3d3b809"
}